dayan_api/__init__.py
dayan_api/connect.py
dayan_api/constants.py
dayan_api/core.py
dayan_api/exception.py
dayan_api/file_operator.py
dayan_api/json_operator.py
dayan_api/paths.py
dayan_api/signature.py
dayan_api/url.py
dayan_api/utils.py
dayan_api/validator.py
dayan_api/operators/__init__.py
dayan_api/operators/env.py
dayan_api/operators/query.py
dayan_api/operators/tag.py
dayan_api/operators/task.py
dayan_api/operators/transmit.py
dayan_api/operators/user.py
dayan_api/schemas/abandonTask.yaml
dayan_api/schemas/add.yaml
dayan_api/schemas/addTaskLabel.yaml
dayan_api/schemas/addUserPluginConfig.yaml
dayan_api/schemas/createTask.yaml
dayan_api/schemas/delete.yaml
dayan_api/schemas/deleteTask.yaml
dayan_api/schemas/deleteTaskLabel.yaml
dayan_api/schemas/deleteUserPluginConfig.yaml
dayan_api/schemas/editUserPluginConfig.yaml
dayan_api/schemas/fullSpeedRendering.yaml
dayan_api/schemas/getOutputUserDirFile.yaml
dayan_api/schemas/getRaySyncUserKey.yaml
dayan_api/schemas/getServerInfo.yaml
dayan_api/schemas/getTaskList.yaml
dayan_api/schemas/getUserPluginConfig.yaml
dayan_api/schemas/list.yaml
dayan_api/schemas/loadTaskProcessImg.yaml
dayan_api/schemas/loadingFrameThumbnail.yaml
dayan_api/schemas/pluginSubmitTask.yaml
dayan_api/schemas/queryAllFrameStats.yaml
dayan_api/schemas/queryAnalyseErrorDetail.yaml
dayan_api/schemas/queryPlatforms.yaml
dayan_api/schemas/querySoftwareDetail.yaml
dayan_api/schemas/queryTaskFrames.yaml
dayan_api/schemas/queryTaskInfo.yaml
dayan_api/schemas/recommitFailFrame.yaml
dayan_api/schemas/recommitTaskFrames.yaml
dayan_api/schemas/recommitTasks.yaml
dayan_api/schemas/schema_v1.yaml
dayan_api/schemas/setDefaultUserPluginConfig.yaml
dayan_api/schemas/setTaskOverTimeStop.yaml
dayan_api/schemas/startTask.yaml
dayan_api/schemas/stopTask.yaml
dayan_api/schemas/stopTaskFrames.yaml
dayan_api/schemas/submitTask.yaml
dayan_api/schemas/task.yaml
dayan_api/schemas/taskJsonFile.yaml
dayan_api/schemas/updateTaskUserLevel.yaml
dayan_api-1.6.dist-info/LICENSE
dayan_api-1.6.dist-info/METADATA
dayan_api-1.6.dist-info/WHEEL
dayan_api-1.6.dist-info/top_level.txt
dayan_api-1.6.dist-info/RECORD
