Metadata-Version: 2.1
Name: dayan-api
Version: 1.6
Summary: A Python-based API for Using Dayan cloud rendering service.
Home-page: https://gitlab.renderbus.com/internal/dayan_api
Author: Shenzhen Rayvision Technology Co., Ltd
Author-email: developer@rayvision.com
License: UNKNOWN
Platform: UNKNOWN
Classifier: Programming Language :: Python
Classifier: Programming Language :: Python :: 3
Requires-Dist: attrs (==19.3.0)
Requires-Dist: cattrs (==1.0.0)
Requires-Dist: tenacity (==6.0.0)
Requires-Dist: future (==0.18.2)
Requires-Dist: requests (==2.23.0)
Requires-Dist: Cerberus (==1.1.0)
Requires-Dist: rayvision-log (>=0.3.3)
